{
  "tasks": [
    {
      "id": "af60",
      "title": "Java",
      "completed": false
    },
    {
      "id": "8294",
      "title": "Learn React",
      "completed": false
    },
    {
      "id": "d57c",
      "title": "React Hook",
      "completed": false
    },
    {
      "id": "b958",
      "title": "React Componets",
      "completed": false
    },
    {
      "id": "e387",
      "title": "web dev",
      "completed": false
    }
  ],
  "users": [
    {
      "id": "1",
      "username": "Admin",
      "email": "admin@gmail.com",
      "password": "123456"
    },
    {
      "id": 1,
      "username": "Omkar",
      "email": "omkar@gmail.com",
      "password": "123456"
    },
    {
      "id": "c580",
      "username": "bittu",
      "email": "bittu@gmail.com",
      "password": "123123"
    },
    {
      "id": "53b8",
      "username": "siddu",
      "email": "sid@gmail.com",
      "password": "1231233"
    }
  ]
}